{
  "version": "v1",
  "suite": "X25519-HKDF-SHA256-CHACHA20POLY1305",
  "vectors": [
    {
      "name": "smoke-1",
      "ns": "myapp",
      "kid": "kid1",
      "request": {
        "action": "smokeTest"
      },
      "plaintext_b64u": "aGVsbG8",
      "eph_seed32_b64u": "AAAAAAAAAAAAAAAAAAAAAAAAAAAAAAAAAAAAAAAAAAA"
    },
    {
      "name": "with-extensions-and-headers",
      "ns": "myapp",
      "kid": "kid-ext-h",
      "request": {
        "action": "withExtensions"
      },
      "extensions": [
        {
          "header": "X-402-Routing",
          "payload": { "service": "test-runner" }
        }
      ],
      "sidecar_as": "headers",
      "public": ["X-402-Routing"],
      "plaintext_b64u": "YXBwLWhlYWRlcnM",
      "eph_seed32_b64u": "AQEBAQEBAQEBAQEBAQEBAQEBAQEBAQEBAQEBAQEA"
    },
    {
      "name": "with-public-request-body",
      "ns": "myapp",
      "kid": "kid-body-j",
      "request": {
        "action": "publicBody"
      },
      "sidecar_as": "json",
      "public": ["request"],
      "plaintext_b64u": "anNvbi1zaWRlY2Fy",
      "eph_seed32_b64u": "AgICAgICAgICAgICAgICAgICAgICAgICAgICAgICA"
    }
  ]
}
